paf_sapgui_cic/elements/__init__.py
paf_sapgui_cic/flows/__init__.py
paf_sapgui_cic/flows/msd_orders/__init__.py
paf_sapgui_cic/flows/msd_orders/aktionshistorie_bearbeiten
paf_sapgui_cic/flows/msd_orders/auftragsdaten_holen
paf_sapgui_cic/flows/msd_orders/beleg_buchen
paf_sapgui_cic/flows/msd_orders/brief_senden
paf_sapgui_cic/flows/msd_orders/fakturaperiodizität
paf_sapgui_cic/flows/msd_orders/kommunikationsdaten_ändern
paf_sapgui_cic/flows/msd_orders/kündigen
paf_sapgui_cic/flows/msd_orders/kündigung_stornieren
paf_sapgui_cic/flows/msd_orders/lieferadresse_ändern
paf_sapgui_cic/flows/msd_orders/löschen
paf_sapgui_cic/flows/msd_orders/objektwechsel
paf_sapgui_cic/flows/msd_orders/optIn_ändern
paf_sapgui_cic/flows/msd_orders/position_löschen
paf_sapgui_cic/flows/msd_orders/reklamation
paf_sapgui_cic/flows/msd_orders/selektiere_auftrag
paf_sapgui_cic/flows/msd_orders/stornieren
paf_sapgui_cic/flows/msd_orders/unbefristete_änderung
paf_sapgui_cic/flows/msd_orders/unterbrechung
paf_sapgui_cic/flows/msd_orders/wiederaufnahme
paf_sapgui_cic/flows/msd_orders/zahlweise
paf_sapgui_cic/flows/msd_orders/änderung_fakturamodalität
paf_sapgui_cic/flows/position_details/__init__.py
paf_sapgui_cic-1.0.16.dist-info/WHEEL
paf_sapgui_cic-1.0.16.dist-info/METADATA
paf_sapgui_cic-1.0.16.dist-info/RECORD
